kotresult/__init__.py
kotresult/__version__.py
kotresult/result.py
kotresult/run_catching.py
kotresult-1.0.1.dist-info/LICENSE
kotresult-1.0.1.dist-info/METADATA
kotresult-1.0.1.dist-info/WHEEL
kotresult-1.0.1.dist-info/RECORD
