Metadata-Version: 2.3
Name: kotresult
Version: 1.0.1
Summary: A Python implementation of the Result monad pattern, inspired by Kotlin
License: MIT
Keywords: result,monad,kotlin,error-handling,functional,type-safe
Author: Vatis
Author-email: vatis@lalcs.com
Requires-Python: >=3.9
Classifier: Development Status :: 5 - Production/Stable
Classifier: Intended Audience :: Developers
Classifier: License :: OSI Approved :: MIT License
Classifier: Programming Language :: Python :: 3
Classifier: Programming Language :: Python :: 3.9
Classifier: Programming Language :: Python :: 3.10
Classifier: Programming Language :: Python :: 3.11
Classifier: Programming Language :: Python :: 3.12
Classifier: Programming Language :: Python :: 3.13
Classifier: Topic :: Software Development :: Libraries :: Python Modules
Classifier: Topic :: Software Development :: Libraries
Classifier: Topic :: Utilities
Classifier: Operating System :: OS Independent
Classifier: Typing :: Typed
Project-URL: Bug Tracker, https://github.com/Lalcs/kotresult/issues
Project-URL: Homepage, https://github.com/Lalcs/kotresult
Project-URL: Repository, https://github.com/Lalcs/kotresult
